docs/source/conf.py
examples/test.py
mlvern/__init__.py
mlvern/core/__init__.py
mlvern/core/forge.py
mlvern/data/__init__.py
mlvern/data/fingerprint.py
mlvern/data/inspect.py
mlvern/data/register.py
mlvern/data/risk_check.py
mlvern/data/statistics.py
mlvern/train/trainer.py
mlvern/utils/__init__.py
mlvern/utils/artifact.py
mlvern/utils/dataset_utils.py
mlvern/utils/environment.py
mlvern/utils/hashing.py
mlvern/utils/registry.py
mlvern/version/run_manager.py
mlvern/visual/auto_plot.py
mlvern/visual/eda.py
mlvern-0.2.0.dist-info/licenses/LICENSE
tests/test_utilities.py
tests/test_versioning.py
tests/data/__init__.py
tests/data/conftest.py
tests/data/edge_cases/test_all_null_column.py
tests/data/edge_cases/test_all_nulls.py
tests/data/edge_cases/test_constant_columns.py
tests/data/edge_cases/test_empty_dataframe.py
tests/data/edge_cases/test_high_cardinality.py
tests/data/edge_cases/test_insufficient_rows.py
tests/data/edge_cases/test_single_row.py
tests/data/integration/test_full_inspection.py
tests/data/integration/test_report_structure.py
tests/data/integration/test_risk_pipeline.py
tests/data/integration/test_save_report.py
tests/data/integration/test_statistics_pipeline.py
tests/data/performance/test_large_dataframe.py
tests/data/risk/test_class_imbalance.py
tests/data/risk/test_data_drift.py
tests/data/risk/test_run_risk_checks.py
tests/data/risk/test_sampling_bias.py
tests/data/risk/test_sensitive_attribute_imbalance.py
tests/data/risk/test_target_leakage.py
tests/data/risk/test_train_test_mismatch.py
tests/data/statistics/test_compute_statistics.py
tests/data/statistics/test_correlations.py
tests/data/statistics/test_dimensionality_signals.py
tests/data/statistics/test_distribution_shape.py
tests/data/statistics/test_feature_target_association.py
tests/data/statistics/test_hypothesis_tests.py
tests/data/statistics/test_interaction_patterns.py
tests/data/statistics/test_numeric_summary.py
tests/data/statistics/test_redundant_features.py
tests/data/statistics/test_vif.py
tests/data/unit/test_init.py
mlvern-0.2.0.dist-info/METADATA
mlvern-0.2.0.dist-info/WHEEL
mlvern-0.2.0.dist-info/top_level.txt
mlvern-0.2.0.dist-info/RECORD
